client/__init__.py
client/add_contact.py
client/database.py
client/del_contact.py
client/errors.py
client/main_window.py
client/main_window_conv.py
client/start_dialog.py
client/transport.py
client/utils.py
common/__init__.py
common/decos.py
common/descripts.py
common/errors.py
common/metaclasses.py
common/utils.py
common/variables.py
log/__init__.py
log/client_log_config.py
log/server_log_config.py
log/variables2.py
unittests/__init__.py
unittests/test_client.py
unittests/test_server.py
unittests/test_utils.py
ApplicationClientServer_client-0.1.dist-info/METADATA
ApplicationClientServer_client-0.1.dist-info/WHEEL
ApplicationClientServer_client-0.1.dist-info/top_level.txt
ApplicationClientServer_client-0.1.dist-info/RECORD
